__init__.py
core/__init__.py
core/diloco.py
distgym-0.0.2.dist-info/licenses/LICENSE
distgym-0.0.2.dist-info/METADATA
distgym-0.0.2.dist-info/WHEEL
distgym-0.0.2.dist-info/top_level.txt
distgym-0.0.2.dist-info/RECORD
