Metadata-Version: 2.4
Name: distgym
Version: 0.0.2
Summary: simulated distributed training
Author-email: Saurav Maheshkar <sauravvmaheshkar@gmail.com>
License-Expression: MIT
Project-URL: repository, https://github.com/SauravMaheshkar/distgym
Classifier: Programming Language :: Python :: 3.10
Classifier: Programming Language :: Python :: 3.11
Classifier: Programming Language :: Python :: 3.12
Requires-Python: >=3.10
License-File: LICENSE
Requires-Dist: torch>=2.7.0
Requires-Dist: wandb
Provides-Extra: examples
Requires-Dist: timm; extra == "examples"
Provides-Extra: dev
Requires-Dist: pre-commit; extra == "dev"
Requires-Dist: ruff; extra == "dev"
Dynamic: license-file
